best/__init__.py
best/integration/__init__.py
best/unit/__init__.py
best/unit/conftest.py
best/unit/test_glue_session.py
best/unit/test_glue_session_demo.py
best/unit/test_session_apis.py
pifacecad-0.7.8.dist-info/LICENSE.txt
pifacecad-0.7.8.dist-info/METADATA
pifacecad-0.7.8.dist-info/WHEEL
pifacecad-0.7.8.dist-info/top_level.txt
pifacecad-0.7.8.dist-info/RECORD
